cerevox_mcp_server/__init__.py
cerevox_mcp_server/__main__.py
cerevox_mcp_server-0.1.0.dist-info/licenses/LICENSE
cerevox_mcp_server-0.1.0.dist-info/METADATA
cerevox_mcp_server-0.1.0.dist-info/WHEEL
cerevox_mcp_server-0.1.0.dist-info/top_level.txt
cerevox_mcp_server-0.1.0.dist-info/RECORD
