Metadata-Version: 2.4
Name: cerevox-mcp-server
Version: 0.1.0
Summary: MCP server exposing Cerevox AI APIs (Lexa, Hippo, Account) for document parsing, RAG search, and account management
Author-email: Cerevox AI <support@cerevox.ai>
License: MIT
Project-URL: Homepage, https://github.com/CerevoxAI/cerevox-mcp-server
Project-URL: Documentation, https://docs.cerevox.ai
Project-URL: Repository, https://github.com/CerevoxAI/cerevox-mcp-server
Project-URL: Issues, https://github.com/CerevoxAI/cerevox-mcp-server/issues
Keywords: mcp,cerevox,document-parsing,rag,ai,llm
Classifier: Development Status :: 3 - Alpha
Classifier: Intended Audience :: Developers
Classifier: License :: OSI Approved :: MIT License
Classifier: Programming Language :: Python :: 3
Classifier: Programming Language :: Python :: 3.9
Classifier: Programming Language :: Python :: 3.10
Classifier: Programming Language :: Python :: 3.11
Classifier: Programming Language :: Python :: 3.12
Classifier: Programming Language :: Python :: 3.13
Requires-Python: >=3.9
License-File: LICENSE
Requires-Dist: cerevox>=0.2.0
Requires-Dist: mcp>=0.9.0
Provides-Extra: dev
Requires-Dist: pytest>=7.0.0; extra == "dev"
Requires-Dist: pytest-asyncio>=0.21.0; extra == "dev"
Requires-Dist: black>=23.0.0; extra == "dev"
Requires-Dist: mypy>=1.0.0; extra == "dev"
Requires-Dist: ruff>=0.1.0; extra == "dev"
Dynamic: license-file
